nlp_models/__init__.py
nlp_models/base/__init__.py
nlp_models/base/data.py
nlp_models/base/io.py
nlp_models/base/layers.py
nlp_models/base/loss.py
nlp_models/base/metrics.py
nlp_models/base/utils.py
nlp_models/bert_classifier/__init__.py
nlp_models/bert_classifier/bert.py
nlp_models/bert_classifier/predict.py
nlp_models/bert_classifier/train.py
nlp_models/cmd/__init__.py
nlp_models/cmd/cli.py
nlp_models/llm/__init__.py
nlp_models/llm/apps.py
nlp_models/llm/base.py
nlp_models/llm/llms.py
nlp_models/llm/prompts.py
nlp_models/llm/vectordbs.py
nlp_models/multi_task_model/__init__.py
nlp_models/multi_task_model/mtl.py
nlp_models/multi_task_model/trainer.py
nlp_models-4.2.2.dist-info/LICENSE
nlp_models-4.2.2.dist-info/METADATA
nlp_models-4.2.2.dist-info/WHEEL
nlp_models-4.2.2.dist-info/entry_points.txt
nlp_models-4.2.2.dist-info/top_level.txt
nlp_models-4.2.2.dist-info/RECORD
