Metadata-Version: 2.1
Name: nlp-models
Version: 4.2.2
Summary: Transformers based NLP models
Home-page: https://github.com/minggnim/nlp-models
Author: Ming Gao
Author-email: ming_gao@outlook.com
Classifier: Development Status :: 4 - Beta
Classifier: Programming Language :: Python
Classifier: Programming Language :: Python :: 3.6
Classifier: Programming Language :: Python :: 3.7
Classifier: Programming Language :: Python :: 3.8
Classifier: Programming Language :: Python :: 3.9
Classifier: Programming Language :: Python :: 3.10
Classifier: Programming Language :: Python :: 3.11
Classifier: License :: OSI Approved :: MIT License
Classifier: Operating System :: OS Independent
Requires-Python: >=3.6
License-File: LICENSE
Requires-Dist: torch
Requires-Dist: torchmetrics
Requires-Dist: transformers
Requires-Dist: langchain
Requires-Dist: ctransformers
Provides-Extra: full
Requires-Dist: tqdm ; extra == 'full'
